tests/__init__.py
tests/test_base.py
tests/test_events.py
tests/test_matches.py
tests/test_scoring.py
tests/test_sequence.py
tests/test_wrestlers.py
wrestling/__init__.py
wrestling/base.py
wrestling/events.py
wrestling/matches.py
wrestling/scoring.py
wrestling/sequence.py
wrestling/wrestlers.py
wrestling-0.4.7.dist-info/LICENSE
wrestling-0.4.7.dist-info/METADATA
wrestling-0.4.7.dist-info/WHEEL
wrestling-0.4.7.dist-info/top_level.txt
wrestling-0.4.7.dist-info/RECORD
