Metadata-Version: 2.1
Name: wrestling
Version: 0.4.7
Summary: A package for wrestling statistics.
Home-page: https://github.com/nanthony007/wrestling/
Author: Nicholas Anthony
Author-email: nanthony007@gmail.com
License: UNKNOWN
Platform: UNKNOWN
Requires-Dist: attrs
